docl
