Metadata-Version: 1.0
Name: docl
Version: 0.41
Summary: Cloudify Docker dev tools
Home-page: UNKNOWN
Author: GigaSpaces
Author-email: cosmo-admin@gigaspaces.com
License: Apache License, Version 2.0
Platform: UNKNOWN
